{
  "position_info": {
    "part": 15,
    "rank": 10,
    "global_position": 513,
    "move_coordinate": "F2",
    "turn_number": 20,
    "npz_file": "1906C337F5CDAFA9.npz",
    "board_tensor_file": "pos_513/board.npy",
    "sgf_file": "pos_513/game.sgf"
  },
  "nmf_analysis": {
    "activation_strength": 0.893511176109314,
    "rank_in_part": 10,
    "activation_in_other_parts": [
      136.13038635253906,
      748.4791259765625,
      0.0,
      261.6993103027344,
      14.408442497253418,
      0.0,
      0.0,
      0.10408740490674973,
      0.0,
      0.031185269355773926,
      0.0,
      0.0,
      0.0,
      0.0,
      0.0,
      0.893511176109314,
      0.0,
      0.0,
      0.0,
      0.027422502636909485,
      0.0,
      0.019665390253067017,
      0.0,
      0.0,
      0.0
    ],
    "channel_activity": [
      49,
      3,
      3,
      0,
      0,
      0,
      0,
      0,
      0,
      1,
      1,
      1,
      1,
      1,
      0,
      0,
      0,
      0,
      3,
      3,
      0,
      0
    ],
    "top_active_channels": [
      [
        0,
        49
      ],
      [
        1,
        3
      ],
      [
        2,
        3
      ],
      [
        18,
        3
      ],
      [
        19,
        3
      ]
    ],
    "total_board_activity": 66
  },
  "go_pattern_analysis": {
    "move_type": "corner",
    "game_phase": "opening",
    "turn_number": 20,
    "policy_entropy": 0.7515409361757097,
    "policy_confidence": 0.8033088235294118,
    "top_policy_moves": [
      {
        "coord": "(1,5)",
        "percentage": 80.3,
        "count": 437
      },
      {
        "coord": "(3,1)",
        "percentage": 19.1,
        "count": 104
      },
      {
        "coord": "(3,5)",
        "percentage": 0.6,
        "count": 3
      }
    ],
    "total_policy_counts": 544
  },
  "part_comparison": {
    "uniqueness_score": 0.0011923456331714988,
    "similar_positions": [
      2354,
      5019,
      2470,
      3394,
      3642
    ],
    "part_rank": 10,
    "max_other_part_activation": 748.4791259765625,
    "activation_percentile": 99.8485536877177
  }
}