{
  "position_info": {
    "part": 3,
    "rank": 12,
    "global_position": 1650,
    "move_coordinate": "PASS",
    "turn_number": 1,
    "npz_file": "1D638D50844BD930.npz",
    "board_tensor_file": "pos_1650/board.npy",
    "sgf_file": "pos_1650/game.sgf"
  },
  "nmf_analysis": {
    "activation_strength": 381.1131896972656,
    "rank_in_part": 12,
    "activation_in_other_parts": [
      1255.9619140625,
      0.0,
      88.3341293334961,
      381.1131896972656,
      93.17085266113281,
      0.7323184609413147,
      0.0,
      0.03334123641252518,
      0.0,
      0.1578749120235443,
      0.0,
      0.3350295126438141,
      0.0,
      0.0,
      0.0,
      0.2953369915485382,
      0.0,
      0.0,
      0.0,
      0.0,
      0.0,
      0.0,
      0.17202375829219818,
      0.0,
      0.0
    ],
    "channel_activity": [
      49,
      18,
      9,
      0,
      0,
      0,
      0,
      0,
      0,
      0,
      1,
      0,
      1,
      0,
      0,
      0,
      3,
      0,
      29,
      20,
      14,
      13
    ],
    "top_active_channels": [
      [
        0,
        49
      ],
      [
        18,
        29
      ],
      [
        19,
        20
      ],
      [
        1,
        18
      ],
      [
        20,
        14
      ]
    ],
    "total_board_activity": 157
  },
  "go_pattern_analysis": {
    "move_type": "pass",
    "game_phase": "opening",
    "turn_number": 1,
    "policy_entropy": 2.979647153859596,
    "policy_confidence": 0.4991568296795953,
    "top_policy_moves": [
      {
        "coord": "PASS",
        "percentage": 49.9,
        "count": 296
      },
      {
        "coord": "(0,2)",
        "percentage": 6.2,
        "count": 37
      },
      {
        "coord": "(0,4)",
        "percentage": 5.1,
        "count": 30
      },
      {
        "coord": "(1,2)",
        "percentage": 4.0,
        "count": 24
      },
      {
        "coord": "(0,6)",
        "percentage": 3.9,
        "count": 23
      }
    ],
    "total_policy_counts": 593
  },
  "part_comparison": {
    "uniqueness_score": 0.23280128836631775,
    "similar_positions": [
      3361,
      6298,
      3415,
      5660,
      2930
    ],
    "part_rank": 12,
    "max_other_part_activation": 1255.9619140625,
    "activation_percentile": 99.81826442526125
  }
}