{
  "position_info": {
    "part": 2,
    "rank": 8,
    "global_position": 4910,
    "move_coordinate": "D2",
    "turn_number": 1,
    "npz_file": "B330F9C802154800.npz",
    "board_tensor_file": "pos_4910/board.npy",
    "sgf_file": "pos_4910/game.sgf"
  },
  "nmf_analysis": {
    "activation_strength": 138.02865600585938,
    "rank_in_part": 8,
    "activation_in_other_parts": [
      682.0753173828125,
      303.6019287109375,
      138.02865600585938,
      4.748969554901123,
      34.39241027832031,
      7.7702460289001465,
      0.0,
      0.9206443428993225,
      0.0,
      0.0,
      0.0,
      0.0,
      0.0,
      0.0,
      49.41643142700195,
      0.0,
      0.0,
      0.0,
      0.0,
      0.0,
      0.2718546688556671,
      0.0,
      0.04373961687088013,
      0.0,
      0.0
    ],
    "channel_activity": [
      49,
      5,
      6,
      0,
      0,
      1,
      0,
      0,
      0,
      1,
      1,
      1,
      1,
      1,
      0,
      1,
      0,
      0,
      5,
      6,
      0,
      0
    ],
    "top_active_channels": [
      [
        0,
        49
      ],
      [
        2,
        6
      ],
      [
        19,
        6
      ],
      [
        1,
        5
      ],
      [
        18,
        5
      ]
    ],
    "total_board_activity": 78
  },
  "go_pattern_analysis": {
    "move_type": "side",
    "game_phase": "opening",
    "turn_number": 1,
    "policy_entropy": 1.1122937860419837,
    "policy_confidence": 0.6929260450160771,
    "top_policy_moves": [
      {
        "coord": "(1,3)",
        "percentage": 69.3,
        "count": 431
      },
      {
        "coord": "(6,1)",
        "percentage": 26.4,
        "count": 164
      },
      {
        "coord": "(3,5)",
        "percentage": 3.4,
        "count": 21
      },
      {
        "coord": "(0,3)",
        "percentage": 0.6,
        "count": 4
      },
      {
        "coord": "(0,2)",
        "percentage": 0.3,
        "count": 2
      }
    ],
    "total_policy_counts": 622
  },
  "part_comparison": {
    "uniqueness_score": 0.16830627620220184,
    "similar_positions": [
      770,
      4243,
      771,
      1568,
      5417
    ],
    "part_rank": 8,
    "max_other_part_activation": 682.0753173828125,
    "activation_percentile": 99.87884295017416
  }
}