{
  "position_info": {
    "part": 24,
    "rank": 15,
    "global_position": 1139,
    "move_coordinate": "D5",
    "turn_number": 13,
    "npz_file": "1D638D50844BD930.npz",
    "board_tensor_file": "pos_1139/board.npy",
    "sgf_file": "pos_1139/game.sgf"
  },
  "nmf_analysis": {
    "activation_strength": 0.5319036841392517,
    "rank_in_part": 15,
    "activation_in_other_parts": [
      0.14703819155693054,
      0.03203196078538895,
      0.04843760281801224,
      0.0,
      0.07891254872083664,
      0.09985946863889694,
      0.05169166997075081,
      0.03936668857932091,
      0.07792848348617554,
      0.23746106028556824,
      0.2675027549266815,
      0.09491875767707825,
      0.3362744450569153,
      0.10982260853052139,
      0.055636607110500336,
      0.15493658185005188,
      0.09417929500341415,
      0.17328791320323944,
      0.04317851737141609,
      0.0449473075568676,
      0.01545849721878767,
      0.07516328990459442,
      0.18945971131324768,
      0.15179000794887543,
      0.5319036841392517
    ],
    "channel_activity": [
      49,
      5,
      5,
      0,
      1,
      3,
      0,
      0,
      0,
      1,
      1,
      1,
      1,
      1,
      1,
      0,
      0,
      0,
      0,
      0,
      0,
      0
    ],
    "top_active_channels": [
      [
        0,
        49
      ],
      [
        1,
        5
      ],
      [
        2,
        5
      ],
      [
        5,
        3
      ],
      [
        4,
        1
      ]
    ],
    "total_board_activity": 69
  },
  "go_pattern_analysis": {
    "move_type": "side",
    "game_phase": "opening",
    "turn_number": 13,
    "policy_entropy": 0.060451491752102224,
    "policy_confidence": 0.9942196531791907,
    "top_policy_moves": [
      {
        "coord": "(4,3)",
        "percentage": 99.4,
        "count": 516
      },
      {
        "coord": "(3,5)",
        "percentage": 0.2,
        "count": 1
      },
      {
        "coord": "(1,0)",
        "percentage": 0.2,
        "count": 1
      },
      {
        "coord": "(2,0)",
        "percentage": 0.2,
        "count": 1
      }
    ],
    "total_policy_counts": 519
  },
  "part_comparison": {
    "uniqueness_score": 0.6126665472984314,
    "similar_positions": [
      3326,
      6265,
      2925,
      6312,
      1641
    ],
    "part_rank": 15,
    "max_other_part_activation": 0.3362744450569153,
    "activation_percentile": 99.77283053157655
  }
}