{
  "position_info": {
    "part": 28,
    "rank": 19,
    "global_position": 2640,
    "move_coordinate": "A1",
    "turn_number": 1,
    "npz_file": "76F9EC3EB6A76AA0.npz",
    "board_tensor_file": "pos_2640/board.npy",
    "sgf_file": "pos_2640/game.sgf"
  },
  "nmf_analysis": {
    "activation_strength": 0.5054990649223328,
    "rank_in_component": 19,
    "activation_in_other_components": [
      0.005621488206088543,
      0.13440726697444916,
      0.0,
      0.0,
      0.002887602662667632,
      0.02380196750164032,
      0.08451481908559799,
      0.042678188532590866,
      0.008066938258707523,
      0.0641622245311737,
      0.008888966403901577,
      0.026768309995532036,
      0.024662602692842484,
      0.029312821105122566,
      0.0,
      0.02191769704222679,
      0.0,
      0.0007361946627497673,
      0.0,
      0.03171897679567337,
      0.0,
      0.029471607878804207,
      0.0,
      0.026014354079961777,
      0.047145843505859375,
      0.0,
      0.0,
      0.020168256014585495,
      0.5054990649223328,
      0.14420326054096222,
      0.02908768132328987,
      0.008849232457578182,
      0.13324162364006042,
      0.1013394147157669,
      0.27910909056663513,
      0.01230199821293354,
      0.2616860270500183,
      0.09424523264169693,
      0.0,
      0.10520230978727341,
      0.0,
      0.1482921689748764,
      0.0,
      0.04921089857816696,
      0.07702420651912689,
      0.1498212367296219,
      0.1433716118335724,
      0.13041558861732483,
      0.2735927700996399,
      0.2972017824649811
    ],
    "channel_activity": [
      49,
      11,
      13,
      1,
      2,
      0,
      0,
      0,
      0,
      1,
      1,
      1,
      0,
      0,
      3,
      2,
      0,
      3,
      0,
      0,
      0,
      0
    ],
    "top_active_channels": [
      [
        0,
        49
      ],
      [
        2,
        13
      ],
      [
        1,
        11
      ],
      [
        14,
        3
      ],
      [
        17,
        3
      ]
    ],
    "total_board_activity": 87
  },
  "go_pattern_analysis": {
    "move_type": "corner",
    "game_phase": "opening",
    "turn_number": 1,
    "policy_entropy": 5.643856189774725,
    "policy_confidence": 0.02,
    "top_policy_moves": [
      {
        "coord": "PASS",
        "percentage": 2.0,
        "count": 1
      },
      {
        "coord": "(1,5)",
        "percentage": 2.0,
        "count": 1
      },
      {
        "coord": "(3,1)",
        "percentage": 2.0,
        "count": 1
      },
      {
        "coord": "(3,0)",
        "percentage": 2.0,
        "count": 1
      },
      {
        "coord": "(2,6)",
        "percentage": 2.0,
        "count": 1
      }
    ],
    "total_policy_counts": 50
  },
  "component_comparison": {
    "uniqueness_score": 0.629747748374939,
    "similar_positions": [
      1568,
      1567,
      1566,
      1565,
      1569
    ],
    "component_rank": 19,
    "max_other_component_activation": 0.2972017824649811,
    "activation_percentile": 99.71225200666363
  }
}