{
  "position_info": {
    "part": 0,
    "rank": 6,
    "global_position": 1466,
    "move_coordinate": "A1",
    "turn_number": 1,
    "npz_file": "1D638D50844BD930.npz",
    "board_tensor_file": "pos_1466/board.npy",
    "sgf_file": "pos_1466/game.sgf"
  },
  "nmf_analysis": {
    "activation_strength": 4270.01904296875,
    "rank_in_part": 6,
    "activation_in_other_parts": [
      4270.01904296875,
      0.0,
      95.01795959472656,
      121.24002838134766,
      57.223052978515625,
      0.775763750076294,
      0.2643294036388397,
      0.0,
      0.0,
      0.1774810552597046,
      0.0,
      0.3193436563014984,
      0.0,
      0.0,
      0.0,
      0.8454458713531494,
      0.2972223162651062,
      0.5914207696914673,
      0.4760919213294983,
      0.0,
      0.0,
      0.0,
      0.0,
      0.0,
      0.14390607178211212
    ],
    "channel_activity": [
      49,
      12,
      16,
      0,
      0,
      1,
      0,
      0,
      0,
      0,
      1,
      0,
      1,
      0,
      0,
      0,
      1,
      0,
      20,
      29,
      11,
      12
    ],
    "top_active_channels": [
      [
        0,
        49
      ],
      [
        19,
        29
      ],
      [
        18,
        20
      ],
      [
        2,
        16
      ],
      [
        1,
        12
      ]
    ],
    "total_board_activity": 153
  },
  "go_pattern_analysis": {
    "move_type": "corner",
    "game_phase": "opening",
    "turn_number": 1,
    "policy_entropy": 5.643856189774725,
    "policy_confidence": 0.02,
    "top_policy_moves": [
      {
        "coord": "PASS",
        "percentage": 2.0,
        "count": 1
      },
      {
        "coord": "(1,5)",
        "percentage": 2.0,
        "count": 1
      },
      {
        "coord": "(3,1)",
        "percentage": 2.0,
        "count": 1
      },
      {
        "coord": "(3,0)",
        "percentage": 2.0,
        "count": 1
      },
      {
        "coord": "(2,6)",
        "percentage": 2.0,
        "count": 1
      }
    ],
    "total_policy_counts": 50
  },
  "part_comparison": {
    "uniqueness_score": 0.9723905324935913,
    "similar_positions": [
      6387,
      934,
      933,
      1177,
      349
    ],
    "part_rank": 6,
    "max_other_part_activation": 121.24002838134766,
    "activation_percentile": 99.90913221263062
  }
}