{
  "position_info": {
    "part": 37,
    "rank": 12,
    "global_position": 1572,
    "move_coordinate": "D7",
    "turn_number": 16,
    "npz_file": "1D638D50844BD930.npz",
    "board_tensor_file": "pos_1572/board.npy",
    "sgf_file": "pos_1572/game.sgf"
  },
  "nmf_analysis": {
    "activation_strength": 0.3059447705745697,
    "rank_in_part": 12,
    "activation_in_other_parts": [
      0.06325620412826538,
      0.07256459444761276,
      0.0,
      0.004205118864774704,
      0.010505067184567451,
      0.0,
      0.07752762734889984,
      0.021489273756742477,
      0.0,
      0.01112821139395237,
      0.0,
      0.006608557887375355,
      0.010492157191038132,
      0.012548436410725117,
      0.0,
      0.025304628536105156,
      0.005617683287709951,
      0.0003431689692661166,
      0.011031641624867916,
      0.012021672911942005,
      0.0,
      0.007551438175141811,
      0.0,
      0.0,
      0.018412388861179352,
      0.004028188064694405,
      0.0,
      0.003933558240532875,
      0.16494961082935333,
      0.005509258713573217,
      0.08904708176851273,
      0.03401738405227661,
      0.02428332529962063,
      0.24110451340675354,
      0.09836666285991669,
      0.11312173306941986,
      0.11570348590612411,
      0.3059447705745697,
      0.09753013402223587,
      0.15733560919761658,
      0.15468499064445496,
      0.05085119605064392,
      0.03500926122069359,
      0.0517386868596077,
      0.16755250096321106,
      0.06929612904787064,
      0.3054439127445221,
      0.21327146887779236,
      0.15832330286502838,
      0.40266773104667664
    ],
    "channel_activity": [
      49,
      8,
      8,
      0,
      2,
      0,
      0,
      0,
      0,
      1,
      1,
      1,
      1,
      1,
      0,
      1,
      1,
      0,
      0,
      0,
      0,
      0
    ],
    "top_active_channels": [
      [
        0,
        49
      ],
      [
        1,
        8
      ],
      [
        2,
        8
      ],
      [
        4,
        2
      ],
      [
        9,
        1
      ]
    ],
    "total_board_activity": 74
  },
  "go_pattern_analysis": {
    "move_type": "side",
    "game_phase": "opening",
    "turn_number": 16,
    "policy_entropy": 0.5094631447674222,
    "policy_confidence": 0.9172749391727494,
    "top_policy_moves": [
      {
        "coord": "(6,3)",
        "percentage": 91.7,
        "count": 377
      },
      {
        "coord": "(0,2)",
        "percentage": 5.6,
        "count": 23
      },
      {
        "coord": "(3,5)",
        "percentage": 1.9,
        "count": 8
      },
      {
        "coord": "(1,5)",
        "percentage": 0.7,
        "count": 3
      }
    ],
    "total_policy_counts": 411
  },
  "part_comparison": {
    "uniqueness_score": 0.43175187706947327,
    "similar_positions": [
      6255,
      4369,
      4370,
      4709,
      2517
    ],
    "part_rank": 12,
    "max_other_part_activation": 0.40266773104667664,
    "activation_percentile": 99.81826442526125
  }
}