{
  "position_info": {
    "part": 4,
    "rank": 20,
    "global_position": 481,
    "move_coordinate": "E3",
    "turn_number": 23,
    "npz_file": "1906C337F5CDAFA9.npz",
    "board_tensor_file": "pos_481/board.npy",
    "sgf_file": "pos_481/game.sgf"
  },
  "nmf_analysis": {
    "activation_strength": 0.8211259245872498,
    "rank_in_part": 20,
    "activation_in_other_parts": [
      0.4543549120426178,
      0.37347522377967834,
      0.0,
      0.049918316304683685,
      0.8211259245872498,
      0.015825482085347176,
      0.0,
      0.0,
      0.03327007219195366,
      0.2793736159801483,
      0.019578544422984123,
      0.006702464073896408,
      0.001261614030227065,
      0.0,
      0.0,
      0.0,
      0.5015220046043396,
      0.0,
      0.006921127438545227,
      0.0,
      0.0,
      0.015125678852200508,
      0.06119820475578308,
      0.0,
      0.13297559320926666
    ],
    "channel_activity": [
      49,
      0,
      1,
      0,
      0,
      0,
      0,
      0,
      0,
      1,
      0,
      0,
      0,
      0,
      0,
      0,
      0,
      0,
      0,
      49,
      0,
      0
    ],
    "top_active_channels": [
      [
        0,
        49
      ],
      [
        19,
        49
      ],
      [
        2,
        1
      ],
      [
        9,
        1
      ],
      [
        1,
        0
      ]
    ],
    "total_board_activity": 100
  },
  "go_pattern_analysis": {
    "move_type": "corner",
    "game_phase": "opening",
    "turn_number": 23,
    "policy_entropy": 1.965812732361599,
    "policy_confidence": 0.3431952662721893,
    "top_policy_moves": [
      {
        "coord": "(2,4)",
        "percentage": 34.3,
        "count": 58
      },
      {
        "coord": "(4,3)",
        "percentage": 23.7,
        "count": 40
      },
      {
        "coord": "(4,4)",
        "percentage": 22.5,
        "count": 38
      },
      {
        "coord": "(2,3)",
        "percentage": 19.5,
        "count": 33
      }
    ],
    "total_policy_counts": 169
  },
  "part_comparison": {
    "uniqueness_score": 0.6208197474479675,
    "similar_positions": [
      6366,
      4410,
      2582,
      1821,
      4993
    ],
    "part_rank": 20,
    "max_other_part_activation": 0.5015220046043396,
    "activation_percentile": 99.69710737543541
  }
}