{
  "position_info": {
    "part": 14,
    "rank": 13,
    "global_position": 651,
    "move_coordinate": "E2",
    "turn_number": 29,
    "npz_file": "1906C337F5CDAFA9.npz",
    "board_tensor_file": "pos_651/board.npy",
    "sgf_file": "pos_651/game.sgf"
  },
  "nmf_analysis": {
    "activation_strength": 0.6116430163383484,
    "rank_in_part": 13,
    "activation_in_other_parts": [
      0.22079876065254211,
      0.20525750517845154,
      0.20480510592460632,
      0.08390974253416061,
      0.10879571735858917,
      0.12169256806373596,
      0.17278912663459778,
      0.29844382405281067,
      0.04445260763168335,
      0.0,
      0.24721281230449677,
      0.03519367054104805,
      0.08182018995285034,
      0.3391928970813751,
      0.6116430163383484,
      0.05448199436068535,
      0.009942673146724701,
      0.03286830335855484,
      0.024124164134263992,
      0.06905830651521683,
      0.04655374214053154,
      0.06857777386903763,
      0.026295974850654602,
      0.22139033675193787,
      0.026166904717683792
    ],
    "channel_activity": [
      49,
      9,
      15,
      0,
      0,
      0,
      0,
      0,
      0,
      1,
      0,
      1,
      1,
      1,
      0,
      0,
      0,
      0,
      20,
      29,
      0,
      0
    ],
    "top_active_channels": [
      [
        0,
        49
      ],
      [
        19,
        29
      ],
      [
        18,
        20
      ],
      [
        2,
        15
      ],
      [
        1,
        9
      ]
    ],
    "total_board_activity": 126
  },
  "go_pattern_analysis": {
    "move_type": "corner",
    "game_phase": "opening",
    "turn_number": 29,
    "policy_entropy": 1.6023070002945299,
    "policy_confidence": 0.625,
    "top_policy_moves": [
      {
        "coord": "(1,4)",
        "percentage": 62.5,
        "count": 175
      },
      {
        "coord": "PASS",
        "percentage": 21.8,
        "count": 61
      },
      {
        "coord": "(5,2)",
        "percentage": 8.2,
        "count": 23
      },
      {
        "coord": "(1,3)",
        "percentage": 4.3,
        "count": 12
      },
      {
        "coord": "(5,1)",
        "percentage": 1.4,
        "count": 4
      }
    ],
    "total_policy_counts": 280
  },
  "part_comparison": {
    "uniqueness_score": 0.6432687044143677,
    "similar_positions": [
      778,
      4226,
      2137,
      3949,
      5083
    ],
    "part_rank": 13,
    "max_other_part_activation": 0.3391928970813751,
    "activation_percentile": 99.80311979403301
  }
}