{
  "position_info": {
    "part": 9,
    "rank": 5,
    "global_position": 5967,
    "move_coordinate": "B4",
    "turn_number": 1,
    "npz_file": "E3CD9898B9AFF870.npz",
    "board_tensor_file": "pos_5967/board.npy",
    "sgf_file": "pos_5967/game.sgf"
  },
  "nmf_analysis": {
    "activation_strength": 0.7171357870101929,
    "rank_in_part": 5,
    "activation_in_other_parts": [
      2626.74365234375,
      162.0679168701172,
      31.196598052978516,
      47.71626663208008,
      4.955504417419434,
      16.059551239013672,
      0.14306768774986267,
      10.13417911529541,
      0.25569283962249756,
      0.7171357870101929,
      46.95684051513672,
      0.09389902651309967,
      0.0,
      0.2834851145744324,
      38.73204803466797,
      0.11532928794622421,
      0.0,
      0.0,
      0.0,
      0.0,
      0.0,
      0.0,
      0.0,
      0.0,
      0.2115613967180252
    ],
    "channel_activity": [
      49,
      6,
      5,
      1,
      1,
      1,
      0,
      0,
      0,
      1,
      1,
      1,
      1,
      1,
      0,
      0,
      0,
      0,
      6,
      5,
      0,
      0
    ],
    "top_active_channels": [
      [
        0,
        49
      ],
      [
        1,
        6
      ],
      [
        18,
        6
      ],
      [
        2,
        5
      ],
      [
        19,
        5
      ]
    ],
    "total_board_activity": 79
  },
  "go_pattern_analysis": {
    "move_type": "side",
    "game_phase": "opening",
    "turn_number": 1,
    "policy_entropy": 0.3196980057548076,
    "policy_confidence": 0.9550359712230215,
    "top_policy_moves": [
      {
        "coord": "(3,1)",
        "percentage": 95.5,
        "count": 531
      },
      {
        "coord": "(4,1)",
        "percentage": 3.4,
        "count": 19
      },
      {
        "coord": "(3,0)",
        "percentage": 0.5,
        "count": 3
      },
      {
        "coord": "(6,5)",
        "percentage": 0.2,
        "count": 1
      },
      {
        "coord": "(1,0)",
        "percentage": 0.2,
        "count": 1
      }
    ],
    "total_policy_counts": 556
  },
  "part_comparison": {
    "uniqueness_score": 0.0002729387197177857,
    "similar_positions": [
      5518,
      4598,
      3374,
      3597,
      3693
    ],
    "part_rank": 5,
    "max_other_part_activation": 2626.74365234375,
    "activation_percentile": 99.92427684385885
  }
}