{
  "position_info": {
    "part": 21,
    "rank": 1,
    "global_position": 2298,
    "move_coordinate": "A1",
    "turn_number": 27,
    "npz_file": "76F9EC3EB6A76AA0.npz",
    "board_tensor_file": "pos_2298/board.npy",
    "sgf_file": "pos_2298/game.sgf"
  },
  "nmf_analysis": {
    "activation_strength": 0.5539337992668152,
    "rank_in_part": 1,
    "activation_in_other_parts": [
      2706.35205078125,
      36.43716049194336,
      72.13011932373047,
      10.680061340332031,
      36.4468994140625,
      0.0,
      0.20203545689582825,
      56.09266662597656,
      0.22706690430641174,
      0.0,
      4.319014549255371,
      0.0,
      0.0,
      0.0,
      9.479265213012695,
      0.0,
      0.0,
      0.0,
      0.05829276144504547,
      0.0019475370645523071,
      0.0,
      0.5539337992668152,
      0.0,
      0.0,
      0.11826320737600327
    ],
    "channel_activity": [
      49,
      16,
      17,
      0,
      2,
      6,
      0,
      0,
      0,
      1,
      1,
      1,
      1,
      1,
      0,
      0,
      0,
      0,
      16,
      17,
      0,
      0
    ],
    "top_active_channels": [
      [
        0,
        49
      ],
      [
        2,
        17
      ],
      [
        19,
        17
      ],
      [
        1,
        16
      ],
      [
        18,
        16
      ]
    ],
    "total_board_activity": 128
  },
  "go_pattern_analysis": {
    "move_type": "corner",
    "game_phase": "opening",
    "turn_number": 27,
    "policy_entropy": 5.643856189774725,
    "policy_confidence": 0.02,
    "top_policy_moves": [
      {
        "coord": "PASS",
        "percentage": 2.0,
        "count": 1
      },
      {
        "coord": "(1,5)",
        "percentage": 2.0,
        "count": 1
      },
      {
        "coord": "(3,1)",
        "percentage": 2.0,
        "count": 1
      },
      {
        "coord": "(3,0)",
        "percentage": 2.0,
        "count": 1
      },
      {
        "coord": "(2,6)",
        "percentage": 2.0,
        "count": 1
      }
    ],
    "total_policy_counts": 50
  },
  "part_comparison": {
    "uniqueness_score": 0.0002046372537733987,
    "similar_positions": [
      5535,
      776,
      5533,
      5534,
      3912
    ],
    "part_rank": 1,
    "max_other_part_activation": 2706.35205078125,
    "activation_percentile": 99.98485536877178
  }
}